philtest/__init__.py
philtest/__version__.py
philtest/calulate.py
philtest-0.1.0.dist-info/licenses/LICENSE
philtest-0.1.0.dist-info/WHEEL
philtest-0.1.0.dist-info/METADATA
philtest-0.1.0.dist-info/RECORD
