Metadata-Version: 2.4
Name: philtest
Version: 0.1.0
Summary: phil-pypi-test
Author: Example Author
Author-email: Example Author <author@example.com>
License-Expression: Apache-2.0
License-File: LICENSE
Classifier: Programming Language :: Python :: 3
Classifier: Operating System :: OS Independent
Requires-Python: >=3.14
